setup.py
rpclib/__init__.py
rpclib/_base.py
rpclib/application.py
rpclib/decorator.py
rpclib/error.py
rpclib/service.py
rpclib.egg-info/PKG-INFO
rpclib.egg-info/SOURCES.txt
rpclib.egg-info/dependency_links.txt
rpclib.egg-info/not-zip-safe
rpclib.egg-info/requires.txt
rpclib.egg-info/top_level.txt
rpclib/auxproc/__init__.py
rpclib/auxproc/_base.py
rpclib/auxproc/sync.py
rpclib/auxproc/thread.py
rpclib/client/__init__.py
rpclib/client/_base.py
rpclib/client/http.py
rpclib/client/zeromq.py
rpclib/client/twisted/__init__.py
rpclib/const/__init__.py
rpclib/const/ansi_color.py
rpclib/const/http.py
rpclib/const/suffix.py
rpclib/const/xml_ns.py
rpclib/interface/__init__.py
rpclib/interface/_base.py
rpclib/interface/wsdl/__init__.py
rpclib/interface/wsdl/wsdl11.py
rpclib/interface/xml_schema/__init__.py
rpclib/interface/xml_schema/_base.py
rpclib/interface/xml_schema/model.py
rpclib/model/__init__.py
rpclib/model/_base.py
rpclib/model/binary.py
rpclib/model/complex.py
rpclib/model/enum.py
rpclib/model/fault.py
rpclib/model/primitive.py
rpclib/model/table.py
rpclib/protocol/__init__.py
rpclib/protocol/_base.py
rpclib/protocol/dictobj.py
rpclib/protocol/html.py
rpclib/protocol/http.py
rpclib/protocol/csv/__init__.py
rpclib/protocol/json/__init__.py
rpclib/protocol/msgpack/__init__.py
rpclib/protocol/soap/__init__.py
rpclib/protocol/soap/mime.py
rpclib/protocol/soap/soap11.py
rpclib/protocol/xml/__init__.py
rpclib/protocol/xml/_base.py
rpclib/protocol/xml/model.py
rpclib/server/__init__.py
rpclib/server/_base.py
rpclib/server/http.py
rpclib/server/null.py
rpclib/server/wsgi.py
rpclib/server/zeromq.py
rpclib/server/django/__init__.py
rpclib/server/twisted/__init__.py
rpclib/test/__init__.py
rpclib/test/sort_wsdl.py
rpclib/test/test_cdict.py
rpclib/test/test_null_server.py
rpclib/test/test_service.py
rpclib/test/test_soap.py
rpclib/test/test_soft_validation.py
rpclib/test/test_sqlalchemy.py
rpclib/test/interface/__init__.py
rpclib/test/interface/test_bare_interface.py
rpclib/test/interface/test_xml_schema.py
rpclib/test/interop/__init__.py
rpclib/test/interop/_test_soap_client_base.py
rpclib/test/interop/test_httprpc.py
