Metadata-Version: 1.1
Name: rpclib
Version: 2.8.0-rc
Summary: A transport and architecture agnostic rpc (de)serialization library that focuses on making small, rpc-oriented messaging work.
Home-page: http://github.com/arskom/rpclib
Author: Burak Arslan
Author-email: burak+rpclib@arskom.com.tr
License: LGPL-2.1
Keywords: soap,wsdl,wsgi,zeromq,rest,rpc,json,http
Platform: UNKNOWN
Classifier: Programming Language :: Python
Classifier: Programming Language :: Python :: 2
Classifier: Programming Language :: Python :: 2.4
Classifier: Programming Language :: Python :: 2.5
Classifier: Programming Language :: Python :: 2.6
Classifier: Programming Language :: Python :: 2.7
Classifier: Operating System :: OS Independent
Classifier: Natural Language :: English
Classifier: Development Status :: 4 - Beta
Classifier: Intended Audience :: Developers
Classifier: Topic :: Internet :: WWW/HTTP :: Dynamic Content
